MANIFEST.in
README
nest.py
py_treap.py
setup.py
treap.py
treap.egg-info/PKG-INFO
treap.egg-info/SOURCES.txt
treap.egg-info/dependency_links.txt
treap.egg-info/top_level.txt