Metadata-Version: 1.1
Name: treap
Version: 2.0.5
Summary: Python implementation of treaps
Home-page: http://stromberg.dnsalias.org/~dstromberg/treap/
Author: Daniel Richard Stromberg
Author-email: strombrg@gmail.com
License: Apache v2
Platform: Cross platform
Classifier: Development Status :: 5 - Production/Stable
Classifier: Intended Audience :: Developers
Classifier: Programming Language :: Python :: 2.7
Classifier: Programming Language :: Python :: 3
